release/__init__.py
rodmena-0.0.1.dist-info/licenses/LICENSE
rodmena-0.0.1.dist-info/METADATA
rodmena-0.0.1.dist-info/WHEEL
rodmena-0.0.1.dist-info/top_level.txt
rodmena-0.0.1.dist-info/RECORD
