Metadata-Version: 2.4
Name: rodmena
Version: 0.0.1
Summary: A basic 'Hello World' package.
Home-page: https://github.com/rodmena-limited/rodmena
Author: Farshid Ashouri
Author-email: farsheed.ashouri@gmail.com
Classifier: Programming Language :: Python :: 3
Classifier: License :: OSI Approved :: MIT License
Classifier: Operating System :: OS Independent
Requires-Python: >=3.6
License-File: LICENSE
Dynamic: author
Dynamic: author-email
Dynamic: classifier
Dynamic: description
Dynamic: description-content-type
Dynamic: home-page
Dynamic: license-file
Dynamic: requires-python
Dynamic: summary
